intentpy/__init__.py
intentpy/context.py
intentpy/core.py
intentpy/registry.py
intentpy/runtime.py
intentpy-0.1.0.dist-info/METADATA
intentpy-0.1.0.dist-info/WHEEL
intentpy-0.1.0.dist-info/top_level.txt
intentpy-0.1.0.dist-info/RECORD
