Metadata-Version: 2.4
Name: intentpy
Version: 0.1.0
Summary: Declarative intent-based execution with preconditions, fallbacks, and nested intent tracing
Author: Siddhant Sukhatankar
License: MIT
Project-URL: Homepage, https://github.com/yourusername/intentpy
Project-URL: Repository, https://github.com/yourusername/intentpy
Keywords: intent,control-flow,workflow,architecture,reliability
Classifier: Programming Language :: Python :: 3
Classifier: License :: OSI Approved :: MIT License
Classifier: Operating System :: OS Independent
Classifier: Intended Audience :: Developers
Classifier: Topic :: Software Development :: Libraries
Requires-Python: >=3.8
